dj_mongohq_url.py
dj_mongohq_url-0.0.3.dist-info/DESCRIPTION.rst
dj_mongohq_url-0.0.3.dist-info/METADATA
dj_mongohq_url-0.0.3.dist-info/metadata.json
dj_mongohq_url-0.0.3.dist-info/RECORD
dj_mongohq_url-0.0.3.dist-info/top_level.txt
dj_mongohq_url-0.0.3.dist-info/WHEEL
