Metadata-Version: 2.0
Name: dj-mongohq-url
Version: 0.0.3
Summary: Use MongoDB URLs in your Django Application.
Home-page: https://github.com/ferrix/dj-mongohq-url
Author: Ferrix Hovi
Author-email: ferrix+github@ferrix.fi
License: BSD
Platform: any
Classifier: Environment :: Web Environment
Classifier: Intended Audience :: Developers
Classifier: License :: OSI Approved :: BSD License
Classifier: Operating System :: OS Independent
Classifier: Programming Language :: Python
Classifier: Topic :: Internet :: WWW/HTTP :: Dynamic Content
Classifier: Topic :: Software Development :: Libraries :: Python Modules
Requires-Dist: six
